performline/__init__.py
performline/__init__.pyc
performline/cli.py
performline/client.py
performline/cliutils.py
performline/testing.py
performline/embedded/__init__.py
performline/embedded/__init__.pyc
performline/embedded/stdlib/__init__.py
performline/embedded/stdlib/__init__.pyc
performline/embedded/stdlib/clients/__init__.py
performline/embedded/stdlib/clients/__init__.pyc
performline/embedded/stdlib/clients/rest/__init__.py
performline/embedded/stdlib/clients/rest/__init__.pyc
performline/embedded/stdlib/clients/rest/exceptions.py
performline/embedded/stdlib/clients/rest/exceptions.pyc
performline/embedded/stdlib/clients/rest/mock_test.py
performline/embedded/stdlib/clients/rest/models.py
performline/embedded/stdlib/clients/rest/models.pyc
performline/embedded/stdlib/clients/rest/models_test.py
performline/embedded/stdlib/clients/rest/responses.py
performline/embedded/stdlib/clients/rest/responses.pyc
performline/embedded/stdlib/clients/rest/responses_test.py
performline/embedded/stdlib/clients/rest/rest_test.py
performline/embedded/stdlib/clients/rest/utils.py
performline/embedded/stdlib/clients/rest/utils.pyc
performline/embedded/stdlib/clients/rest/__pycache__/mock_test.cpython-27-PYTEST.pyc
performline/embedded/stdlib/clients/rest/__pycache__/models_test.cpython-27-PYTEST.pyc
performline/embedded/stdlib/clients/rest/__pycache__/responses_test.cpython-27-PYTEST.pyc
performline/embedded/stdlib/clients/rest/__pycache__/rest_test.cpython-27-PYTEST.pyc
performline/embedded/stdlib/utils/__init__.py
performline/embedded/stdlib/utils/__init__.pyc
performline/embedded/stdlib/utils/convert.py
performline/embedded/stdlib/utils/convert.pyc
performline/embedded/stdlib/utils/convert_test.py
performline/embedded/stdlib/utils/dicts.py
performline/embedded/stdlib/utils/dicts.pyc
performline/embedded/stdlib/utils/dicts_test.py
performline/embedded/stdlib/utils/json.py
performline/embedded/stdlib/utils/json.pyc
performline-1.0.3.dist-info/METADATA
performline-1.0.3.dist-info/RECORD
performline-1.0.3.dist-info/WHEEL
performline-1.0.3.dist-info/entry_points.txt
performline-1.0.3.dist-info/top_level.txt
