Metadata-Version: 2.1
Name: performline
Version: 1.0.3
Summary: Client library for using the public PerformLine Compliance API
Home-page: https://github.com/PerformLine/python-performline-client
Author: PerformLine Engineering
Author-email: tech+api@performline.com
License: UNKNOWN
Platform: UNKNOWN
Classifier: Development Status :: 3 - Alpha
Classifier: Natural Language :: English
Classifier: License :: OSI Approved :: BSD License
Classifier: Programming Language :: Python
Classifier: Programming Language :: Python :: 3
Classifier: Topic :: Internet :: WWW/HTTP
Classifier: Topic :: Office/Business
Classifier: Environment :: Console
Classifier: Operating System :: MacOS :: MacOS X
Classifier: Operating System :: POSIX
Classifier: Operating System :: POSIX :: Linux
Classifier: Operating System :: Microsoft :: Windows
Classifier: Intended Audience :: Customer Service
Classifier: Intended Audience :: Financial and Insurance Industry
Requires-Dist: click
Requires-Dist: requests
Requires-Dist: pyyaml
Requires-Dist: statsd
Requires-Dist: python-dateutil (<2.7.0)
Requires-Dist: six
Requires-Dist: requests-mock
